[{"id":"5","firstname":"Vassily","lastname":"Kandinsky","artistsExhibitedWithConnection":{"edges":[{"startdate":"1908","title":"Салон 1909","node":{"firstname":"Ivan","id":"2542","lastname":"Sacharov"}},{"startdate":"1908","title":"Салон 1909","node":{"firstname":"Aleksandr","id":"2094","lastname":"Shervashidze"}},{"startdate":"1908","title":"Салон 1909","node":{"firstname":"Nicholas","id":"2027","lastname":"Roerich"}},{"startdate":"1908","title":"Салон 1909","node":{"firstname":"Dmitry","id":"2073","lastname":"Mitrokhin"}},{"startdate":"1908","title":"Салон 1909","node":{"firstname":"M. K.","id":"2512","lastname":"Čiurlionis"}},{"startdate":"1908","title":"Салон 1909","node":{"firstname":"Aleksandr","id":"2003","lastname":"Golovin"}},{"startdate":"1908","title":"Салон 1909","node":{"firstname":"Alexandre","id":"27","lastname":"Benois"}},{"startdate":"1908","title":"Салон 1909","node":{"firstname":"Dmitry","id":"2044","lastname":"Stelletsky"}},{"startdate":"1908","title":"Салон 1909","node":{"firstname":"Konstantin","id":"2005","lastname":"Yuon"}},{"startdate":"1908","title":"Салон 1909","node":{"firstname":"Isaak","id":"2011","lastname":"Levitan"}},{"startdate":"1908","title":"Салон 1909","node":{"firstname":"Mykhail","id":"2070","lastname":"Latri"}},{"startdate":"1908","title":"Салон 1909","node":{"firstname":"Juho","id":"2900","lastname":"Rissanen"}},{"startdate":"1908","title":"Салон 1909","node":{"firstname":"Viktor","id":"8554","lastname":"Vasnetsov"}},{"startdate":"1908","title":"Салон 1909","node":{"firstname":"Maria Vasilievna","id":"2056","lastname":"Iakunchikova-Veber"}},{"startdate":"1908","title":"Салон 1909","node":{"firstname":"Aleksandr Fedorovich","id":"133","lastname":"Gaush"}},{"startdate":"1908","title":"Салон 1909","node":{"firstname":"Léon","id":"14","lastname":"Bakst"}},{"startdate":"1908","title":"Салон 1909","node":{"firstname":"Igor","id":"1793","lastname":"Grabar"}},{"startdate":"1908","title":"Салон 1909","node":{"firstname":"Yevgeny","id":"2010","lastname":"Lansere"}},{"startdate":"1908","title":"Салон 1909","node":{"firstname":"Konstantin","id":"2007","lastname":"Korovin"}},{"startdate":"1908","title":"Салон 1909","node":{"firstname":"Boris","id":"2009","lastname":"Kustodiyev"}},{"startdate":"1908","title":"Салон 1909","node":{"firstname":"Sergey Vasil'yevich","id":"2017","lastname":"Malyutin"}},{"startdate":"1908","title":"Салон 1909","node":{"firstname":"Liubov Nikolaevna","id":"1968","lastname":"Gaush"}},{"startdate":"1908","title":"Салон 1909","node":{"firstname":"Jan","id":"2387","lastname":"Ciągliński"}},{"startdate":"1908","title":"Салон 1909","node":{"firstname":"Petr Ignat'evič","id":"43","lastname":"Bromirskij"}},{"startdate":"1908","title":"Салон 1909","node":{"firstname":"Valentin","id":"2037","lastname":"Serov"}},{"startdate":"1908","title":"Салон 1909","node":{"firstname":"Mikhail Aleksandrovic","id":"2598","lastname":"Šitov"}},{"startdate":"1908","title":"Салон 1909","node":{"firstname":"Aleksander","id":"2596","lastname":"Kholopov"}},{"startdate":"1908","title":"Салон 1909","node":{"firstname":"Vasily","id":"2500","lastname":"Surikov"}},{"startdate":"1908","title":"Салон 1909","node":{"firstname":"Nikolay","id":"2064","lastname":"Lansere"}},{"startdate":"1908","title":"Салон 1909","node":{"firstname":"Konstantin","id":"2587","lastname":"Evseev"}},{"startdate":"1908","title":"Салон 1909","node":{"firstname":"Andrey","id":"2026","lastname":"Ryabushkin"}},{"startdate":"1908","title":"Салон 1909","node":{"firstname":"Ivan","id":"2089","lastname":"Fomin"}},{"startdate":"1908","title":"Салон 1909","node":{"firstname":"Leonid","id":"2263","lastname":"Pasternak"}},{"startdate":"1908","title":"Салон 1909","node":{"firstname":"Elena","id":"2591","lastname":"Luksch-Makowsky"}},{"startdate":"1908","title":"Салон 1909","node":{"firstname":"Nikolaj Petrovič","id":"2001","lastname":"Feofilaktov"}},{"startdate":"1908","title":"Салон 1909","node":{"firstname":"Ivan","id":"2588","lastname":"Zhaltovsky"}},{"startdate":"1908","title":"Салон 1909","node":{"firstname":"Karl","id":"2902","lastname":"Flinta"}},{"startdate":"1908","title":"Салон 1909","node":{"firstname":"Ivan","id":"1992","lastname":"Bilibin"}},{"startdate":"1908","title":"Салон 1909","node":{"firstname":"Modest Aleksandrovic","id":"2000","lastname":"Durnow"}},{"startdate":"1908","title":"XV Выставка Картин Московскаго Товарищества Художников","node":{"firstname":"Viktor","id":"2903","lastname":"Zamyraylo"}},{"startdate":"1908","title":"XV Выставка Картин Московскаго Товарищества Художников","node":{"firstname":"N. I.","id":"4219","lastname":"Bastarev-Vasilyev"}},{"startdate":"1908","title":"XV Выставка Картин Московскаго Товарищества Художников","node":{"firstname":"K. V.","id":"5358","lastname":"Orlov"}},{"startdate":"1908","title":"XV Выставка Картин Московскаго Товарищества Художников","node":{"firstname":"D. V.","id":"4233","lastname":"Shemyakin"}},{"startdate":"1908","title":"XV Выставка Картин Московскаго Товарищества Художников","node":{"firstname":"M. F.","id":"4225","lastname":"Petin"}},{"startdate":"1908","title":"XV Выставка Картин Московскаго Товарищества Художников","node":{"firstname":"Léon","id":"4221","lastname":"Zack"}},{"startdate":"1908","title":"XV Выставка Картин Московскаго Товарищества Художников","node":{"firstname":"M. S.","id":"4231","lastname":"Chuyko"}},{"startdate":"1908","title":"XV Выставка Картин Московскаго Товарищества Художников","node":{"firstname":"Sergey","id":"4220","lastname":"Beklemishev"}},{"startdate":"1908","title":"XV Выставка Картин Московскаго Товарищества Художников","node":{"firstname":"Oleksandr","id":"35","lastname":"Bohomazov"}},{"startdate":"1908","title":"XV Выставка Картин Московскаго Товарищества Художников","node":{"firstname":"Vladimir","id":"4197","lastname":"Orlov"}},{"startdate":"1908","title":"XV Выставка Картин Московскаго Товарищества Художников","node":{"firstname":"Nikolay","id":"4230","lastname":"Sobolev"}},{"startdate":"1908","title":"XV Выставка Картин Московскаго Товарищества Художников","node":{"firstname":"E.","id":"4222","lastname":"Kuznetsov"}},{"startdate":"1908","title":"XV Выставка Картин Московскаго Товарищества Художников","node":{"firstname":"V. K.","id":"3771","lastname":"Dolin"}},{"startdate":"1908","title":"XV Выставка Картин Московскаго Товарищества Художников","node":{"firstname":"Petr Nikandroivč","id":"1894","lastname":"Mironovic"}},{"startdate":"1908","title":"XV Выставка Картин Московскаго Товарищества Художников","node":{"firstname":"Vladimir","id":"4228","lastname":"Rossinsky"}},{"startdate":"1908","title":"XV Выставка Картин Московскаго Товарищества Художников","node":{"firstname":"Vasyl'","id":"4223","lastname":"Masyutyn"}}]}}]